interactive_click/__about__.py
interactive_click/__init__.py
interactive_click/core.py
interactive_click/py.typed
interactive_click-0.0.2.dist-info/METADATA
interactive_click-0.0.2.dist-info/WHEEL
interactive_click-0.0.2.dist-info/licenses/LICENSE.txt
interactive_click-0.0.2.dist-info/RECORD
