Metadata-Version: 2.1
Name: interactive-click
Version: 0.0.2
Project-URL: Documentation, https://github.com/elazarcoh/interactive-click#readme
Project-URL: Issues, https://github.com/elazarcoh/interactive-click/issues
Project-URL: Source, https://github.com/elazarcoh/interactive-click
Author: Elazar
License-Expression: MIT
License-File: LICENSE.txt
Classifier: Development Status :: 4 - Beta
Classifier: Programming Language :: Python
Classifier: Programming Language :: Python :: 3.7
Classifier: Programming Language :: Python :: 3.8
Classifier: Programming Language :: Python :: 3.9
Classifier: Programming Language :: Python :: 3.10
Classifier: Programming Language :: Python :: 3.11
Classifier: Programming Language :: Python :: Implementation :: CPython
Classifier: Programming Language :: Python :: Implementation :: PyPy
Requires-Python: >=3.7
Requires-Dist: click
Requires-Dist: prompt-toolkit
Requires-Dist: questionary
